agent.py
cli.py
init.py
openiap/__init__.py
openiap/client.py
openiap/protowrap.py
proto/ace_pb2.py
proto/ace_pb2.pyi
proto/ace_pb2_grpc.py
proto/base_pb2.py
proto/base_pb2.pyi
proto/base_pb2_grpc.py
proto/querys_pb2.py
proto/querys_pb2.pyi
proto/querys_pb2_grpc.py
proto/queues_pb2.py
proto/queues_pb2.pyi
proto/queues_pb2_grpc.py
proto/watch_pb2.py
proto/watch_pb2.pyi
proto/watch_pb2_grpc.py
proto/workitems_pb2.py
proto/workitems_pb2.pyi
proto/workitems_pb2_grpc.py
openiap-0.0.37.dist-info/LICENSE.md
openiap-0.0.37.dist-info/METADATA
openiap-0.0.37.dist-info/WHEEL
openiap-0.0.37.dist-info/top_level.txt
openiap-0.0.37.dist-info/RECORD
