Metadata-Version: 2.1
Name: openiap
Version: 0.0.37
Summary: Simple openiap api wrapper using proto
Author-email: OpenIAP ApS / Allan Zimmerman <info@openiap.io>
Project-URL: Homepage, https://github.com/openiap/pyapi
Project-URL: Bug Tracker, https://discourse.openiap.io/c/issues-and-feature-requests
Project-URL: Funding, https://github.com/sponsors/skadefro
Classifier: Programming Language :: Python :: 3
Classifier: License :: OSI Approved :: Mozilla Public License 2.0 (MPL 2.0)
Classifier: Operating System :: OS Independent
License-File: LICENSE.md
Requires-Dist: protobuf
Requires-Dist: grpcio
Requires-Dist: websockets
